pidgen2/__init__.py
pidgen2/add_brunel.py
pidgen2/blabla.py
pidgen2/cache.py
pidgen2/correct.py
pidgen2/corrector.py
pidgen2/create_correction_example.py
pidgen2/create_example.py
pidgen2/create_photon_correction_example.py
pidgen2/create_resampling_example.py
pidgen2/datasets.py
pidgen2/density_estimation.py
pidgen2/explore_samples.py
pidgen2/init.py
pidgen2/legacy_correct.py
pidgen2/legacy_resample.py
pidgen2/list_mc_samples.py
pidgen2/list_mc_variables.py
pidgen2/list_samples.py
pidgen2/list_variables.py
pidgen2/mc_datasets.py
pidgen2/plotting.py
pidgen2/resample.py
pidgen2/resampler.py
pidgen2/resampling.py
pidgen2/resampling_new.py
pidgen2/run3_datasets.py
pidgen2/systematics.py
pidgen2/tuples.py
pidgen2/validate.py
pidgen2/data/samples.json
pidgen2/examples/example_correct.py
pidgen2/examples/example_correct_photon.py
pidgen2/examples/example_numpy_corrector.py
pidgen2/examples/example_numpy_resampler.py
pidgen2/examples/example_resample.py
pidgen2/examples/example_resample_run3.py
pidgen2/samples/K_Dstar2Dpi.py
pidgen2/samples/K_Dstar2Dpi_M.py
pidgen2/samples/K_Dstar2Dpi_P.py
pidgen2/samples/K_Dstar2Dpi_PIDKgt4.py
pidgen2/samples/K_Dstar2Dpi_PtEta.py
pidgen2/samples/K_Dstar2Dpi_scale.py
pidgen2/samples/__init__.py
pidgen2/samples/e_B2JpsieeK.py
pidgen2/samples/e_B2JpsieeK_Brem.py
pidgen2/samples/e_B2JpsieeK_NoBrem.py
pidgen2/samples/gamma_B2KstarGamma.py
pidgen2/samples/gamma_B2KstarGammaType0.py
pidgen2/samples/gamma_B2KstarGammaType1.py
pidgen2/samples/mu_Jpsi2mumu.py
pidgen2/samples/mu_Jpsi2mumu_isMuon.py
pidgen2/samples/mu_Jpsi2mumunopt.py
pidgen2/samples/mu_Jpsi2mumunopt_isMuon.py
pidgen2/samples/p_IncLc.py
pidgen2/samples/p_Lambda2ppi.py
pidgen2/samples/p_Lambda2ppi_Prompt.py
pidgen2/samples/p_Lambda2ppi_Prompt_PIDpgt0.py
pidgen2/samples/p_Lambda2ppi_scale.py
pidgen2/samples/p_Lb2Lcmu.py
pidgen2/samples/p_Lb2Lcpi.py
pidgen2/samples/p_Test.py
pidgen2/samples/pi_Dstar2Dpi.py
pidgen2/samples/pi_Dstar2Dpi_M.py
pidgen2/samples/pi_Dstar2Dpi_P.py
pidgen2-0.4.6.dist-info/licenses/LICENSE
pidgen2-0.4.6.dist-info/METADATA
pidgen2-0.4.6.dist-info/WHEEL
pidgen2-0.4.6.dist-info/entry_points.txt
pidgen2-0.4.6.dist-info/top_level.txt
pidgen2-0.4.6.dist-info/RECORD
