Metadata-Version: 2.4
Name: pidgen2
Version: 0.4.6
Summary: Tools for particle identification (PID) correction for LHCb detector
Home-page: https://gitlab.cern.ch/lhcb-rta/pidgen2
Author: Anton Poluektov
Author-email: anton.poluektov@cern.ch
Project-URL: Bug Tracker, https://gitlab.cern.ch/lhcb-rta/pidgen2/issues
Classifier: Programming Language :: Python :: 3
Classifier: License :: OSI Approved :: GNU General Public License v3 (GPLv3)
Classifier: Operating System :: OS Independent
Requires-Python: >=3.12
License-File: LICENSE
Requires-Dist: numpy>=1.26
Requires-Dist: scipy>=1.14
Requires-Dist: pandas>=2.2
Requires-Dist: matplotlib>=3.9
Requires-Dist: uproot>=5.4
Requires-Dist: xrootd>=5.7
Requires-Dist: fsspec-xrootd>=0.4
Dynamic: license-file
